[
    {
        "Item": "1",
        "Nome": "Camisa Social Manga Longa Azul Claro",
        "Descricao": [
            "camis",
            "social",
            "masculin",
            "mang",
            "long",
            "cor",
            "azul",
            "clar",
            "dispon",
            "tamanh",
            "m",
            "g",
            "gg"
        ],
        "Preco": 109.9
    },
    {
        "Item": "2",
        "Nome": "Calça Jeans Azul Escuro",
        "Descricao": [
            "calc",
            "jeans",
            "unissex",
            "cort",
            "ret",
            "cor",
            "azul",
            "escur",
            "dispon",
            "tamanh",
            "38",
            "40",
            "42",
            "44"
        ],
        "Preco": 99.9
    },
    {
        "Item": "3",
        "Nome": "Saia Jeans Azul Claro",
        "Descricao": [
            "sai",
            "jeans",
            "feminin",
            "cor",
            "azul",
            "clar",
            "cintur",
            "alta",
            "dispon",
            "tamanh",
            "p",
            "m",
            "g"
        ],
        "Preco": 89.9
    },
    {
        "Item": "4",
        "Nome": "Bermuda de Sarja Bege Escuro",
        "Descricao": [
            "bermud",
            "masculin",
            "sarj",
            "cor",
            "beg",
            "escur",
            "dispon",
            "tamanh",
            "38",
            "40",
            "42",
            "44"
        ],
        "Preco": 79.9
    },
    {
        "Item": "5",
        "Nome": "Blusa de Manga Curta Preta",
        "Descricao": [
            "blus",
            "feminin",
            "mang",
            "curt",
            "cor",
            "pret",
            "model",
            "básic",
            "dispon",
            "tamanh",
            "p",
            "m",
            "g"
        ],
        "Preco": 49.9
    },
    {
        "Item": "6",
        "Nome": "Camisa Social Manga Curta Branca",
        "Descricao": [
            "camis",
            "social",
            "masculin",
            "mang",
            "curt",
            "cor",
            "branc",
            "dispon",
            "tamanh",
            "m",
            "g",
            "gg"
        ],
        "Preco": 89.9
    },
    {
        "Item": "7",
        "Nome": "Calça Jeans Preta",
        "Descricao": [
            "calc",
            "jeans",
            "feminin",
            "cor",
            "pret",
            "cort",
            "skinny",
            "dispon",
            "tamanh",
            "36",
            "38",
            "40",
            "42"
        ],
        "Preco": 99.9
    },
    {
        "Item": "8",
        "Nome": "Saia Midi Bege Claro",
        "Descricao": [
            "sai",
            "feminin",
            "tec",
            "lev",
            "cor",
            "beg",
            "clar",
            "cintur",
            "ajust",
            "dispon",
            "tamanh",
            "p",
            "m",
            "g"
        ],
        "Preco": 79.9
    },
    {
        "Item": "9",
        "Nome": "Bermuda Jeans Azul Claro",
        "Descricao": [
            "bermud",
            "jeans",
            "masculin",
            "cor",
            "azul",
            "clar",
            "cort",
            "tradicional",
            "dispon",
            "tamanh",
            "38",
            "40",
            "42",
            "44"
        ],
        "Preco": 89.9
    },
    {
        "Item": "10",
        "Nome": "Blusa Manga Longa Branca",
        "Descricao": [
            "blus",
            "feminin",
            "mang",
            "long",
            "cor",
            "branc",
            "model",
            "básic",
            "dispon",
            "tamanh",
            "p",
            "m",
            "g"
        ],
        "Preco": 69.9
    },
    {
        "Item": "11",
        "Nome": "Camisa Casual Manga Longa Preta",
        "Descricao": [
            "camis",
            "casual",
            "masculin",
            "mang",
            "long",
            "cor",
            "pret",
            "dispon",
            "tamanh",
            "m",
            "g",
            "gg"
        ],
        "Preco": 119.9
    },
    {
        "Item": "12",
        "Nome": "Calça Jeans Azul Claro",
        "Descricao": [
            "calc",
            "jeans",
            "feminin",
            "cor",
            "azul",
            "clar",
            "model",
            "flar",
            "dispon",
            "tamanh",
            "36",
            "38",
            "40",
            "42"
        ],
        "Preco": 129.9
    },
    {
        "Item": "13",
        "Nome": "Saia Curta Jeans Azul Escuro",
        "Descricao": [
            "sai",
            "jeans",
            "feminin",
            "cor",
            "azul",
            "escur",
            "barr",
            "desfi",
            "dispon",
            "tamanh",
            "p",
            "m",
            "g"
        ],
        "Preco": 79.9
    },
    {
        "Item": "14",
        "Nome": "Bermuda de Sarja Preta",
        "Descricao": [
            "bermud",
            "masculin",
            "sarj",
            "cor",
            "pret",
            "bols",
            "later",
            "dispon",
            "tamanh",
            "38",
            "40",
            "42",
            "44"
        ],
        "Preco": 89.9
    },
    {
        "Item": "15",
        "Nome": "Blusa Manga Curta Bege Claro",
        "Descricao": [
            "blus",
            "feminin",
            "mang",
            "curt",
            "cor",
            "beg",
            "clar",
            "gol",
            "arredond",
            "dispon",
            "tamanh",
            "p",
            "m",
            "g"
        ],
        "Preco": 59.9
    }
]